Metadata-Version: 1.0
Name: vnl-distributions
Version: 0.2
Summary: Gaussian and Binomials distributions
Home-page: UNKNOWN
Author: Vinicius Nascimento
Author-email: huevinne@gmail.com
License: UNKNOWN
Platform: UNKNOWN
